.gitignore
LICENSE
MANIFEST.in
README.md
requirements.txt
setup.py
gis_tools.egg-info/PKG-INFO
gis_tools.egg-info/SOURCES.txt
gis_tools.egg-info/dependency_links.txt
gis_tools.egg-info/not-zip-safe
gis_tools.egg-info/requires.txt
gis_tools.egg-info/top_level.txt
gistools/.gitignore
gistools/__init__.py
gistools/conversion.py
gistools/coordinates.py
gistools/database.py
gistools/distance.py
gistools/exceptions.py
gistools/files.py
gistools/geocoding.py
gistools/geometry.py
gistools/graph.py
gistools/layer.py
gistools/network.py
gistools/plotting.py
gistools/projections.py
gistools/raster.py
gistools/stats.py
gistools/surface.py
gistools/topography.py
gistools/utils/__init__.py
gistools/utils/check/__init__.py
gistools/utils/check/descriptor.py
gistools/utils/check/type.py
gistools/utils/check/value.py
gistools/utils/sys/__init__.py
gistools/utils/sys/reader.py
gistools/utils/toolset/__init__.py
gistools/utils/toolset/list.py
gistools/utils/toolset/sqlcsv.py