Metadata-Version: 2.1
Name: gis-tools
Version: 0.17.7
Summary: Some geographical tools for Python developers
Home-page: http://github.com/benjaminpillot/gis-tools
Author: Benjamin Pillot
Author-email: benjaminpillot@riseup.net
License: MIT
Platform: UNKNOWN
Requires-Python: >=3
